semantic_copycat_upmex-1.6.5.dist-info/licenses/LICENSE
upmex/__init__.py
upmex/cli.py
upmex/config.py
upmex/api/__init__.py
upmex/api/clearlydefined.py
upmex/api/ecosystems.py
upmex/api/purldb.py
upmex/api/vulnerablecode.py
upmex/core/__init__.py
upmex/core/extractor.py
upmex/core/models.py
upmex/extractors/__init__.py
upmex/extractors/base.py
upmex/extractors/cocoapods_extractor.py
upmex/extractors/conan_extractor.py
upmex/extractors/conda_extractor.py
upmex/extractors/deb_extractor.py
upmex/extractors/go_extractor.py
upmex/extractors/gradle_extractor.py
upmex/extractors/java_extractor.py
upmex/extractors/npm_extractor.py
upmex/extractors/nuget_extractor.py
upmex/extractors/perl_extractor.py
upmex/extractors/python_extractor.py
upmex/extractors/rpm_extractor.py
upmex/extractors/ruby_extractor.py
upmex/extractors/rust_extractor.py
upmex/licenses/__init__.py
upmex/licenses/oslili_subprocess.py
upmex/licenses/unified_detector.py
upmex/utils/__init__.py
upmex/utils/archive_utils.py
upmex/utils/author_parser.py
upmex/utils/output_formatter.py
upmex/utils/package_detector.py
upmex/utils/patterns.py
semantic_copycat_upmex-1.6.5.dist-info/METADATA
semantic_copycat_upmex-1.6.5.dist-info/WHEEL
semantic_copycat_upmex-1.6.5.dist-info/entry_points.txt
semantic_copycat_upmex-1.6.5.dist-info/top_level.txt
semantic_copycat_upmex-1.6.5.dist-info/RECORD
