Metadata-Version: 2.4
Name: semantic-copycat-upmex
Version: 1.6.5
Summary: Universal Package Metadata Extractor - Extract metadata from various package formats
Author-email: "Oscar Valenzuela B." <oscar.valenzuela.b@gmail.com>
Maintainer-email: "Oscar Valenzuela B." <oscar.valenzuela.b@gmail.com>
License: MIT
Project-URL: Homepage, https://github.com/oscarvalenzuelab/semantic-copycat-upmex
Project-URL: Repository, https://github.com/oscarvalenzuelab/semantic-copycat-upmex
Project-URL: Issues, https://github.com/oscarvalenzuelab/semantic-copycat-upmex/issues
Project-URL: Documentation, https://github.com/oscarvalenzuelab/semantic-copycat-upmex#readme
Project-URL: Changelog, https://github.com/oscarvalenzuelab/semantic-copycat-upmex/blob/main/CHANGELOG.md
Keywords: package,metadata,extractor,license,detection,python,npm,maven,jar,wheel,pypi
Classifier: Development Status :: 5 - Production/Stable
Classifier: Intended Audience :: Developers
Classifier: License :: OSI Approved :: MIT License
Classifier: Operating System :: OS Independent
Classifier: Programming Language :: Python :: 3
Classifier: Programming Language :: Python :: 3.8
Classifier: Programming Language :: Python :: 3.9
Classifier: Programming Language :: Python :: 3.10
Classifier: Programming Language :: Python :: 3.11
Classifier: Programming Language :: Python :: 3.12
Classifier: Topic :: Software Development :: Libraries
Classifier: Topic :: Software Development :: Libraries :: Python Modules
Classifier: Topic :: System :: Archiving :: Packaging
Requires-Python: >=3.8
License-File: LICENSE
Requires-Dist: requests>=2.28.0
Requires-Dist: click>=8.0.0
Requires-Dist: typing-extensions>=4.0.0; python_version < "3.10"
Requires-Dist: semantic-copycat-oslili>=1.5.5
Requires-Dist: toml>=0.10.0
Requires-Dist: zstandard>=0.19.0
Provides-Extra: dev
Requires-Dist: pytest>=7.0.0; extra == "dev"
Requires-Dist: pytest-cov>=4.0.0; extra == "dev"
Requires-Dist: pytest-mock>=3.10.0; extra == "dev"
Requires-Dist: black>=23.0.0; extra == "dev"
Requires-Dist: ruff>=0.1.0; extra == "dev"
Requires-Dist: mypy>=1.0.0; extra == "dev"
Requires-Dist: types-requests; extra == "dev"
Provides-Extra: ml
Requires-Dist: scikit-learn>=1.0.0; extra == "ml"
Requires-Dist: numpy>=1.21.0; extra == "ml"
Provides-Extra: all
Requires-Dist: semantic-copycat-upmex[dev,ml]; extra == "all"
Dynamic: license-file
